LICENSE
MANIFEST.in
README.rst
insynsregistret
requirements.txt
setup.py
insynsregistret/__init__.py
insynsregistret/client.py
insynsregistret/clientcache.py
insynsregistret.egg-info/PKG-INFO
insynsregistret.egg-info/SOURCES.txt
insynsregistret.egg-info/dependency_links.txt
insynsregistret.egg-info/top_level.txt