Metadata-Version: 1.1
Name: insynsregistret
Version: 0.0.2.3
Summary: A client for the Swedish insynsregistret
Home-page: https://github.com/djonsson/insynsregistret
Author: Daniel Jonsson
Author-email: wd.jonsson@gmail.com
License: Copyright (c) 2016 Daniel Jonsson.
